Metadata-Version: 2.1
Name: monopriors
Version: 0.1.0
Summary: Monocular Geometric Priors
Requires-Python: >=3.10.0
